laplace_log/__init__.py
laplace_log/log_lhc.py
laplace_log/utils.py
laplace_log-0.1.0.dist-info/licenses/LICENSE
laplace_log-0.1.0.dist-info/METADATA
laplace_log-0.1.0.dist-info/WHEEL
laplace_log-0.1.0.dist-info/top_level.txt
laplace_log-0.1.0.dist-info/RECORD
