Metadata-Version: 2.4
Name: laplace-log
Version: 0.1.0
Summary: Unified logging utilities for Laplace applications
Author: SemionTche
License-Expression: GPL-3.0-only
Project-URL: Homepage, https://github.com/SemionTche/laplace_log
Project-URL: Repository, https://github.com/SemionTche/laplace_log
Project-URL: Issues, https://github.com/SemionTche/laplace_log/issues
Keywords: logging,laplace,utilities
Classifier: Development Status :: 3 - Alpha
Classifier: Intended Audience :: Developers
Classifier: Programming Language :: Python :: 3
Classifier: Programming Language :: Python :: 3.10
Classifier: Programming Language :: Python :: 3.11
Classifier: Programming Language :: Python :: 3.12
Requires-Python: >=3.10
License-File: LICENSE
Dynamic: license-file
